invcrypt/__init__.py
invcrypt/cli_args.py
invcrypt/config.py
invcrypt/constants.py
invcrypt/info.py
invcrypt/loader.py
invcrypt/main.py
invcrypt/metrics.py
invcrypt/__pycache__/__init__.cpython-312.opt-1.pyc
invcrypt/__pycache__/__init__.cpython-312.pyc
invcrypt/__pycache__/cli_args.cpython-312.opt-1.pyc
invcrypt/__pycache__/cli_args.cpython-312.pyc
invcrypt/__pycache__/config.cpython-312.opt-1.pyc
invcrypt/__pycache__/config.cpython-312.pyc
invcrypt/__pycache__/constants.cpython-312.opt-1.pyc
invcrypt/__pycache__/constants.cpython-312.pyc
invcrypt/__pycache__/crypto_core.cpython-312.opt-1.pyc
invcrypt/__pycache__/hashing.cpython-312.opt-1.pyc
invcrypt/__pycache__/info.cpython-312.opt-1.pyc
invcrypt/__pycache__/info.cpython-312.pyc
invcrypt/__pycache__/loader.cpython-312.opt-1.pyc
invcrypt/__pycache__/loader.cpython-312.pyc
invcrypt/__pycache__/main.cpython-312.opt-1.pyc
invcrypt/__pycache__/main.cpython-312.pyc
invcrypt/__pycache__/matrix.cpython-312.opt-1.pyc
invcrypt/__pycache__/metrics.cpython-312.opt-1.pyc
invcrypt/__pycache__/metrics.cpython-312.pyc
invcrypt/__pycache__/utils.cpython-312.opt-1.pyc
invcrypt-1.0.13.dist-info/licenses/LICENSE
invcrypt-1.0.13.dist-info/METADATA
invcrypt-1.0.13.dist-info/WHEEL
invcrypt-1.0.13.dist-info/entry_points.txt
invcrypt-1.0.13.dist-info/top_level.txt
invcrypt-1.0.13.dist-info/RECORD
