Metadata-Version: 2.4
Name: invcrypt
Version: 1.0.13
Summary: Quantum-safe local file encryption CLI based on Invicra’s proprietary DITG/FTG cryptography.
Home-page: https://github.com/ivarolsson1415/invcrypt-community
Author: INVICRA Technologies AB
Author-email: INVICRA Technologies AB <contact@invicra.com>
License-Expression: LicenseRef-Invicra-Community-2025
Project-URL: Homepage, https://github.com/ivarolsson1415/invcrypt-community
Project-URL: Repository, https://github.com/ivarolsson1415/invcrypt-community
Project-URL: Issues, https://github.com/ivarolsson1415/invcrypt-community/issues
Project-URL: Documentation, https://pypi.org/project/invcrypt/
Keywords: encryption,quantum-safe,post-quantum,cli,cryptography,security,invicra
Classifier: Development Status :: 5 - Production/Stable
Classifier: Intended Audience :: Developers
Classifier: Intended Audience :: Science/Research
Classifier: Topic :: Security :: Cryptography
Classifier: Programming Language :: Python :: 3
Classifier: Programming Language :: Python :: 3.12
Classifier: Operating System :: OS Independent
Requires-Python: >=3.12
License-File: LICENSE
Requires-Dist: tqdm>=4.66.0
Requires-Dist: colorama>=0.4.6
Dynamic: author
Dynamic: home-page
Dynamic: license-file
Dynamic: requires-python
